qsipy/__init__.py
qsipy/tfs.py
qsipy/tms.py
qsipy/trigonometry.py
qsipy-1.0.0.dist-info/WHEEL
qsipy-1.0.0.dist-info/METADATA
qsipy-1.0.0.dist-info/RECORD
