Metadata-Version: 2.1
Name: qsipy
Version: 1.0.0
Summary: Quantum State Interferometry with PYthon.
License: MIT
Author: Quentin Marolleau
Author-email: quentin.marolleau@institutoptique.fr
Requires-Python: >=3.10,<4.0
Classifier: License :: OSI Approved :: MIT License
Classifier: Programming Language :: Python :: 3
Classifier: Programming Language :: Python :: 3.10
Classifier: Programming Language :: Python :: 3.11
Requires-Dist: numpy (>=1.25.0,<2.0.0)
